spatialid/__init__.py
spatialid/dnn.py
spatialid/loader.py
spatialid/loss.py
spatialid/reader.py
spatialid/spatial.py
spatialid/trainer.py
spatialid/transfer.py
SpatialID-1.0.4.dist-info/LICENSE
SpatialID-1.0.4.dist-info/METADATA
SpatialID-1.0.4.dist-info/WHEEL
SpatialID-1.0.4.dist-info/top_level.txt
SpatialID-1.0.4.dist-info/RECORD
