Metadata-Version: 2.1
Name: SpatialID
Version: 1.0.4
Summary: Spatial-ID: a cell typing method for spatially resolved transcriptomics via transfer learning and spatial embedding
Home-page: https://github.com/STOmics/SpatialID.git
Author: zhangchao
Author-email: 1623804006@qq.com
Classifier: Programming Language :: Python :: 3
Classifier: License :: OSI Approved :: MIT License
Classifier: Operating System :: OS Independent
Requires-Python: >=3.8
License-File: LICENSE
Requires-Dist: matplotlib (>=3.7.2)
